yasr/.version
yasr/__init__.py
yasr/cli.py
yasr/logger.py
yasr/models.py
yasr-0.1.2.dist-info/METADATA
yasr-0.1.2.dist-info/WHEEL
yasr-0.1.2.dist-info/entry_points.txt
yasr-0.1.2.dist-info/namespace_packages.txt
yasr-0.1.2.dist-info/top_level.txt
yasr-0.1.2.dist-info/zip-safe
yasr-0.1.2.dist-info/RECORD
