Metadata-Version: 2.1
Name: yasr
Version: 0.1.2
Summary: UNKNOWN
Home-page: UNKNOWN
License: UNKNOWN
Platform: UNKNOWN
Requires-Dist: PyInquirer (==1.0.3)
Requires-Dist: click (==8.1.3)
Requires-Dist: pydantic (==1.9.1)
Requires-Dist: tqdm (==4.64.0)
Requires-Dist: typer (==0.4.2)
